overviewpy/.DS_Store
overviewpy/__init__.py
overviewpy/overviewpy.py
overviewpy-0.1.1.dist-info/LICENSE
overviewpy-0.1.1.dist-info/METADATA
overviewpy-0.1.1.dist-info/WHEEL
overviewpy-0.1.1.dist-info/RECORD
