Metadata-Version: 2.1
Name: overviewpy
Version: 0.1.1
Summary: Easily Extracting Information About Your Data
License: BSD 3-Clause
Author: Cosima Meyer
Requires-Python: >=3.9,<4.0
Classifier: License :: Other/Proprietary License
Classifier: Programming Language :: Python :: 3
Classifier: Programming Language :: Python :: 3.9
Classifier: Programming Language :: Python :: 3.10
Classifier: Programming Language :: Python :: 3.11
Requires-Dist: markdown-include (>=0.8.1,<0.9.0)
Requires-Dist: matplotlib (>=3.7.2,<4.0.0)
Requires-Dist: mkdocs (>=1.4.3,<2.0.0)
Requires-Dist: mkdocs-jupyter (>=0.24.2,<0.25.0)
Requires-Dist: mkdocs-material (>=9.1.19,<10.0.0)
Requires-Dist: mkdocstrings[python] (>=0.22.0,<0.23.0)
Requires-Dist: pandas (>=2.0.3,<3.0.0)
